liquid_babel/__init__.py
liquid_babel/py.typed
liquid_babel/filters/__init__.py
liquid_babel/filters/currency.py
liquid_babel/filters/date_and_time.py
liquid_babel/filters/number.py
liquid_babel/filters/pluralization.py
liquid_babel/filters/translate.py
liquid_babel/filters/unit.py
liquid_babel/messages/__init__.py
liquid_babel/messages/exceptions.py
liquid_babel/messages/extract.py
liquid_babel/messages/translations.py
liquid_babel/tags/__init__.py
liquid_babel/tags/translate.py
liquid_babel-1.0.0.dist-info/LICENSE
liquid_babel-1.0.0.dist-info/METADATA
liquid_babel-1.0.0.dist-info/WHEEL
liquid_babel-1.0.0.dist-info/top_level.txt
liquid_babel-1.0.0.dist-info/RECORD
