Metadata-Version: 2.1
Name: liquid-babel
Version: 1.0.0
Summary: Internationalization for Python Liquid
License: MIT
Project-URL: Documentation, https://jg-rp.github.io/liquid/babel/introduction
Project-URL: Issue Tracker, https://github.com/jg-rp/liquid-babel/issues
Project-URL: Source Code, https://github.com/jg-rp/liquid-babel
Project-URL: Change Log, https://github.com/jg-rp/liquid-babel/blob/main/CHANGES.md
Classifier: Development Status :: 5 - Production/Stable
Classifier: Intended Audience :: Developers
Classifier: License :: OSI Approved :: MIT License
Classifier: Programming Language :: Python :: 3
Classifier: Programming Language :: Python :: 3.7
Classifier: Programming Language :: Python :: 3.8
Classifier: Programming Language :: Python :: 3.9
Classifier: Programming Language :: Python :: 3.10
Classifier: Programming Language :: Python :: 3.11
Classifier: Programming Language :: Python :: Implementation :: CPython
Classifier: Programming Language :: Python :: Implementation :: PyPy
Requires-Python: >=3.7
License-File: LICENSE
Requires-Dist: babel (>=2.10.0)
Requires-Dist: pytz (>=2015.7)
Requires-Dist: python-liquid (>=1.4.4)
Requires-Dist: typing-extensions (>=4.2.0)
